CHANGES.rst
CONTRIBUTORS.rst
MANIFEST.in
README.rst
setup.cfg
setup.py
docs/LICENSE.GPL
docs/LICENSE.rst
docs/index.rst
src/plonetheme/__init__.py
src/plonetheme.clean_blog.egg-info/PKG-INFO
src/plonetheme.clean_blog.egg-info/SOURCES.txt
src/plonetheme.clean_blog.egg-info/dependency_links.txt
src/plonetheme.clean_blog.egg-info/entry_points.txt
src/plonetheme.clean_blog.egg-info/namespace_packages.txt
src/plonetheme.clean_blog.egg-info/not-zip-safe
src/plonetheme.clean_blog.egg-info/requires.txt
src/plonetheme.clean_blog.egg-info/top_level.txt
src/plonetheme/clean_blog/__init__.py
src/plonetheme/clean_blog/configure.zcml
src/plonetheme/clean_blog/interfaces.py
src/plonetheme/clean_blog/setuphandlers.py
src/plonetheme/clean_blog/testing.py
src/plonetheme/clean_blog/browser/__init__.py
src/plonetheme/clean_blog/browser/configure.zcml
src/plonetheme/clean_blog/browser/overrides/.gitkeep
src/plonetheme/clean_blog/browser/overrides/plone.app.contenttypes.behaviors.leadimage.pt
src/plonetheme/clean_blog/browser/static/.gitkeep
src/plonetheme/clean_blog/locales/plonetheme.clean-blog.pot
src/plonetheme/clean_blog/locales/update.sh
src/plonetheme/clean_blog/profiles/default/browserlayer.xml
src/plonetheme/clean_blog/profiles/default/metadata.xml
src/plonetheme/clean_blog/profiles/default/registry.xml
src/plonetheme/clean_blog/profiles/default/theme.xml
src/plonetheme/clean_blog/profiles/uninstall/browserlayer.xml
src/plonetheme/clean_blog/profiles/uninstall/theme.xml
src/plonetheme/clean_blog/tests/__init__.py
src/plonetheme/clean_blog/tests/test_robot.py
src/plonetheme/clean_blog/tests/test_setup.py
src/plonetheme/clean_blog/tests/robot/test_example.robot
src/plonetheme/clean_blog/theme/._LICENSE
src/plonetheme/clean_blog/theme/._README.md
src/plonetheme/clean_blog/theme/._about.html
src/plonetheme/clean_blog/theme/._contact.html
src/plonetheme/clean_blog/theme/._css
src/plonetheme/clean_blog/theme/._fonts
src/plonetheme/clean_blog/theme/._img
src/plonetheme/clean_blog/theme/._js
src/plonetheme/clean_blog/theme/._mail
src/plonetheme/clean_blog/theme/._post.html
src/plonetheme/clean_blog/theme/LICENSE
src/plonetheme/clean_blog/theme/README.md
src/plonetheme/clean_blog/theme/about.html
src/plonetheme/clean_blog/theme/backend.html
src/plonetheme/clean_blog/theme/contact.html
src/plonetheme/clean_blog/theme/index.html
src/plonetheme/clean_blog/theme/index_initial.html
