Metadata-Version: 1.1
Name: plonetheme.clean-blog
Version: 1.0a1
Summary: An installable theme for Plone 5
Home-page: https://pypi.python.org/pypi/plonetheme.clean-blog
Author: Andre Goncalves
Author-email: andre@intk.com
License: GPL version 2
Keywords: Python Plone
Platform: UNKNOWN
Classifier: Environment :: Web Environment
Classifier: Framework :: Plone
Classifier: Framework :: Plone :: 5.0
Classifier: Programming Language :: Python
Classifier: Programming Language :: Python :: 2.7
Classifier: Operating System :: OS Independent
Classifier: License :: OSI Approved :: GNU General Public License v2 (GPLv2)
